mediaquery/__init__.py
mediaquery/media_jk.py
mediaquery/lib/Argument.py
mediaquery/lib/__init__.py
media_jk-0.3.7.dist-info/METADATA
media_jk-0.3.7.dist-info/WHEEL
media_jk-0.3.7.dist-info/entry_points.txt
media_jk-0.3.7.dist-info/top_level.txt
media_jk-0.3.7.dist-info/RECORD
