Metadata-Version: 2.1
Name: media_jk
Version: 0.3.7
Summary: Media_jk is a Wrapper of Mediainfo
Home-page: https://git.selfmade.ninja/jevaa_kharthik/media_jk
Author: Jevaa Kharthik N
Author-email: jevaasureka@gmail.com
